aiomangadex-api/__init__.py
aiomangadexapi/__init__.py
aiomangadexapi-1.1.0.dist-info/LICENCE.txt
aiomangadexapi-1.1.0.dist-info/METADATA
aiomangadexapi-1.1.0.dist-info/WHEEL
aiomangadexapi-1.1.0.dist-info/top_level.txt
aiomangadexapi-1.1.0.dist-info/RECORD
