Metadata-Version: 2.1
Name: aiomangadexapi
Version: 1.1.0
Summary: An asychronous mangadex API wrapper with updates and more!
Home-page: https://github.com/Mudy7/aiomangadexapi
Author: Mudy7
Author-email: retaketurbo@gmail.com
License: UNKNOWN
Platform: UNKNOWN
Classifier: Programming Language :: Python :: 3
Classifier: License :: OSI Approved :: MIT License
Classifier: Operating System :: OS Independent
Requires-Python: >=3.6
Requires-Dist: feedparser
Requires-Dist: aiohttp
Requires-Dist: lxml
